README.md
pyproject.toml
setup.py
gophercorn.egg-info/PKG-INFO
gophercorn.egg-info/SOURCES.txt
gophercorn.egg-info/dependency_links.txt
gophercorn.egg-info/requires.txt
gophercorn.egg-info/top_level.txt
volk/__init__.py
volk/__main__.py
volk/message.py
volk/volk.py
volk/volk2.py
volk/worker.py
volk/wsgi.py