Metadata-Version: 2.4
Name: gophercorn
Version: 0.0.0
Summary: Fast ASGI Server written in Go
Home-page: https://github.com/joegasewicz/volk
Author: joegasewicz
Author-email: joegasewicz <joegasewicz@gmail.com>
License: MIT
Requires-Python: >=3.13
Requires-Dist: twine<7.0.0,>=6.2.0
Dynamic: author
Dynamic: home-page
